LICENSE
README.rst
pyproject.toml
setup.cfg
setup.py
player_on_court/__init__.py
player_on_court/player_on_court.py
player_on_court.egg-info/PKG-INFO
player_on_court.egg-info/SOURCES.txt
player_on_court.egg-info/dependency_links.txt
player_on_court.egg-info/not-zip-safe
player_on_court.egg-info/top_level.txt